examples/usage.py
examples/pretrain/preprocess.py
examples/pretrain/pretrain.py
examples/verification/verify.py
examples/xla-reference/xpreprocess.py
examples/xla-reference/xpretrain.py
voltron/__init__.py
voltron/conf/__init__.py
voltron/conf/accelerators.py
voltron/conf/datasets.py
voltron/conf/models.py
voltron/conf/tracking.py
voltron/datasets/__init__.py
voltron/datasets/datasets.py
voltron/datasets/v1/__init__.py
voltron/datasets/v1/stream_datasets.py
voltron/models/__init__.py
voltron/models/instantiate.py
voltron/models/materialize.py
voltron/models/core/__init__.py
voltron/models/core/vcond.py
voltron/models/core/vdual.py
voltron/models/core/vgen.py
voltron/models/reproductions/__init__.py
voltron/models/reproductions/vmvp.py
voltron/models/reproductions/vr3m.py
voltron/models/reproductions/vrn3m.py
voltron/models/util/__init__.py
voltron/models/util/extraction.py
voltron/models/util/optimization.py
voltron/models/util/transformer.py
voltron/overwatch/__init__.py
voltron/overwatch/overwatch.py
voltron/preprocessing/__init__.py
voltron/preprocessing/core.py
voltron/preprocessing/process.py
voltron/preprocessing/transforms.py
voltron/preprocessing/v1/__init__.py
voltron/preprocessing/v1/process.py
voltron/preprocessing/v1/transforms.py
voltron/preprocessing/v1/utils.py
voltron/util/__init__.py
voltron/util/checkpointing.py
voltron/util/metrics.py
voltron/util/utilities.py
voltron/util/v1/__init__.py
voltron/util/v1/checkpointing.py
voltron/util/v1/distributed.py
voltron/util/v1/random.py
voltron/util/v1/xla_logger.py
voltron_robotics-1.1.0.dist-info/LICENSE
voltron_robotics-1.1.0.dist-info/METADATA
voltron_robotics-1.1.0.dist-info/WHEEL
voltron_robotics-1.1.0.dist-info/top_level.txt
voltron_robotics-1.1.0.dist-info/RECORD
