Metadata-Version: 2.1
Name: voltron-robotics
Version: 1.1.0
Summary: Voltron: Language-Driven Representation Learning for Robotics.
Author-email: Siddharth Karamcheti <skaramcheti@cs.stanford.edu>
License: MIT License
Project-URL: homepage, https://github.com/siddk/voltron-robotics
Project-URL: repository, https://github.com/siddk/voltron-robotics
Project-URL: documentation, https://github.com/siddk/voltron-robotics
Keywords: robotics,representation learning,natural language processing,machine learning
Classifier: Development Status :: 3 - Alpha
Classifier: Intended Audience :: Developers
Classifier: Intended Audience :: Education
Classifier: Intended Audience :: Science/Research
Classifier: License :: OSI Approved :: MIT License
Classifier: Operating System :: OS Independent
Classifier: Programming Language :: Python :: 3
Classifier: Programming Language :: Python :: 3.8
Classifier: Programming Language :: Python :: 3.9
Classifier: Programming Language :: Python :: 3.10
Classifier: Programming Language :: Python :: 3 :: Only
Classifier: Topic :: Scientific/Engineering :: Artificial Intelligence
Requires-Python: >=3.8
License-File: LICENSE
Requires-Dist: av
Requires-Dist: einops
Requires-Dist: gdown
Requires-Dist: google-cloud-storage
Requires-Dist: h5py
Requires-Dist: hurry.filesize
Requires-Dist: hydra-core (==1.1.1)
Requires-Dist: jsonlines
Requires-Dist: omegaconf (==2.1.2)
Requires-Dist: opencv-python
Requires-Dist: pandas
Requires-Dist: rich
Requires-Dist: torch (>=2.0.0)
Requires-Dist: torchvision (>=0.15.0)
Requires-Dist: transformers
Requires-Dist: wandb
Provides-Extra: dev
Requires-Dist: black ; extra == 'dev'
Requires-Dist: ipython ; extra == 'dev'
Requires-Dist: pre-commit ; extra == 'dev'
Requires-Dist: ruff ; extra == 'dev'
